odoo/addons/web_tree_resize_column/README.rst
odoo/addons/web_tree_resize_column/__init__.py
odoo/addons/web_tree_resize_column/__manifest__.py
odoo/addons/web_tree_resize_column/i18n/web_tree_resize_column.pot
odoo/addons/web_tree_resize_column/readme/CONTRIBUTORS.rst
odoo/addons/web_tree_resize_column/readme/CREDITS.rst
odoo/addons/web_tree_resize_column/readme/DESCRIPTION.rst
odoo/addons/web_tree_resize_column/readme/USAGE.rst
odoo/addons/web_tree_resize_column/static/description/icon.png
odoo/addons/web_tree_resize_column/static/description/index.html
odoo/addons/web_tree_resize_column/static/lib/resizableColumns/LICENSE
odoo/addons/web_tree_resize_column/static/lib/resizableColumns/jQuery.resizableColumns.js
odoo/addons/web_tree_resize_column/static/src/js/backend.js
odoo/addons/web_tree_resize_column/templates/assets.xml
odoo11_addon_web_tree_resize_column-11.0.1.0.0.99.dev5.dist-info/METADATA
odoo11_addon_web_tree_resize_column-11.0.1.0.0.99.dev5.dist-info/WHEEL
odoo11_addon_web_tree_resize_column-11.0.1.0.0.99.dev5.dist-info/top_level.txt
odoo11_addon_web_tree_resize_column-11.0.1.0.0.99.dev5.dist-info/RECORD
